quantx_sdk/__init__.py
quantx_sdk/algorithm.py
quantx_sdk/api.py
quantx_sdk/backtest.py
quantx_sdk/backtest_result.py
quantx_sdk/exception.py
quantx_sdk/portfolio.py
quantx_sdk/project.py
quantx_sdk/root.py
quantx_sdk/util.py
quantx_sdk-0.1.10.dist-info/LICENSE
quantx_sdk-0.1.10.dist-info/METADATA
quantx_sdk-0.1.10.dist-info/WHEEL
quantx_sdk-0.1.10.dist-info/top_level.txt
quantx_sdk-0.1.10.dist-info/RECORD
