Metadata-Version: 2.1
Name: quantx-sdk
Version: 0.1.10
Summary: QuantX SDK
Home-page: https://factory.quantx.io/
Author: Smart Trade Inc.
Author-email: dev@smarttrade.co.jp
License: Apache License Version 2.0
Platform: UNKNOWN
License-File: LICENSE
Requires-Dist: requests (>=2.26.0)
Requires-Dist: pandas (==0.23.4)
Requires-Dist: websocket-client (>=1.2.1)
